mountvfs/__init__.py
mountvfs/exceptions.py
mountvfs/nfs.py
mountvfs/sshfs.py
mountvfs/vfs.py
mountvfs-0.1.7.dist-info/LICENSE
mountvfs-0.1.7.dist-info/METADATA
mountvfs-0.1.7.dist-info/NOTICE
mountvfs-0.1.7.dist-info/WHEEL
mountvfs-0.1.7.dist-info/top_level.txt
mountvfs-0.1.7.dist-info/RECORD
