Metadata-Version: 2.1
Name: mountvfs
Version: 0.1.7
Summary: SSHFS, NFS clients.
Home-page: UNKNOWN
Author: Annaz
Author-email: annazabn@gmail.com
License: UNKNOWN
Platform: UNKNOWN
Requires-Python: >=3.6
Requires-Dist: typeguard
